make_password.py
mkpw-1.0.2.dist-info/METADATA
mkpw-1.0.2.dist-info/WHEEL
mkpw-1.0.2.dist-info/entry_points.txt
mkpw-1.0.2.dist-info/top_level.txt
mkpw-1.0.2.dist-info/RECORD
