Metadata-Version: 2.1
Name: mkpw
Version: 1.0.2
Summary: Memorable Password Generator
Home-page: https://github.com/stevemcgrath/mkpw
Author: Steve McGrath
Author-email: steve@mcgrath.sh
License: MIT
Keywords: password passwords
Platform: UNKNOWN
Classifier: Development Status :: 5 - Production/Stable
Classifier: Topic :: System :: Systems Administration
Classifier: Topic :: Utilities
Classifier: License :: OSI Approved :: MIT License
Classifier: Programming Language :: Python :: 3.6
Classifier: Programming Language :: Python :: 3.7
Classifier: Programming Language :: Python :: 3.8
Classifier: Programming Language :: Python :: 3.9
Classifier: Programming Language :: Python :: 3.10
Classifier: Programming Language :: Python :: 3.11
Classifier: Programming Language :: Python :: 3.12
Requires-Dist: typer (>=0.3.2)
Requires-Dist: rich (>=10.2.2)
Requires-Dist: memorable (>=1.0.3)
Requires-Dist: pyperclip (>=1.8.2)
